{"songs": [{"title": "Universe*", "album": "No Pressure", "year": null, "lyrics": "Lyrics from snippet:\n\nBeat 'em to death like No I.D\nStreets full of envy, wanna kill me\n'Cause\u2005I\u2005made a lot\u2005of money and I'm still me\nNow\u2005the dollar bill don't thrill me\nKnow somebody feel me\nNot Logic, but the real me\nUnder the surface I'm rhymin' with purpose\nI know I ain't perfect, I'm Kirk and you irking me\nAll these go-getters ain't what they assert to be\nI am the universe, you Captain Kirk to me\nNothing but regurgitating, far from innovative\nI made it, I'm hated, I'm feelin' elated\nMan, fuck who the greatest\nSoon as I drop it, they play it", "image": "https://images.genius.com/75b9fd3705271c3c10d64dfb3139caf7.900x900x1.jpg"}], "artist": "Logic"}