{"songs": [{"title": "Walk In With Me", "album": null, "year": "2013-03-26", "lyrics": "[Hook: Gucci Mane]\nIf you smokin Reggie Bush\nThen you cannot smoke with me\nIf you wear Fila, prada, then you can\u2019t walk in with me\nIf you ain\u2019t stuffin up a blunt, then y\u2019all niggas can\u2019t smoke with me\nIf you wear fake gold, then you can\u2019t walk in with me\nCan\u2019t walk in with me, yall boys can\u2019t walk in with me\nCan\u2019t walk in with me, girl can\u2019t walk in with me\nCan\u2019t walk in with me, boy you can\u2019t walk in with me\nNah, walk off enemy, girl you can\u2019t walk in with Guwap\n\n[Verse 1: Gucci Mane]\nStop, stop, stop right there\nBitch you know you cannot go\nNow, now, do your hair\nDo your hair you dirty ho\nNah, nah, walk with me nigga\nSwappin nigga can\u2019t walk with me\nNah, nah, I\u2019m big Guwop\nTalk that nigga I\u2019m off that nigga\nShop with a nigga, come shop with a nigga\nBout to go to the mall and shop for her\nLouie bag I bag the road, gotta pull in a guil bars for her\nMy girlfriend so crazy bad, gotta renta cop fo her\nI don\u2019t roll with police man, I\u2019m gonn buy a Glock for her\n\nI\u2019m getting super head, some crazy head\nWhat\u2019s crazy, I\u2019m on top of her\nGot 6\u2019s on my droppin phantom, out the window opera\nI got cake like oprah, cookin dope like oakara\nDon\u2019t call your girl for 30 minutes, I left nut all over her\n\n[Hook: Gucci Mane]\nIf you smokin, reggie bush\nThen you cannot smoke with me\nIf you wear ..fila, prada, then you can\u2019t walk in with me\nIf you ain\u2019t stuffin a blunt, then y\u2019all niggas can\u2019t smoke with me\nIf you wear fake gold, then you can\u2019t walk in with me\nCan\u2019t walk in with me, yall boys can\u2019t walk in with me\nCan\u2019t walk in with me, girl you can\u2019t walk in with me\nCan\u2019t walk in with me, boy you can\u2019t walk in with me\nNah, walk off enemy, girl you can\u2019t walk in with Guwap\n\n[Verse 2: Migos]\nPlayboy I got all them problems, but I am 1017\nYou smokin on your uncle pat hell nah you cannot smoke with me\nYou walk around with levis on but I got on them robin jeans\nMy niggas walk around with bones but nah this ain\u2019t no busy bees\nYou niggas ain\u2019t makin no noise\nWalk straight in the club my boys\nGot niggas that will hit you like floyd\nGot 100 rounds in a choppa toy\nI got a rollie on not mike kors\nThere\u2019s 100 bricks, check the scoreboard\nThrowing bricks like I hit the back-board\nYou got the swag bag get the rap for\nNah you can\u2019t walk in with me\nWith those levis on and ...\nDon\u2019t need pat no blunt to me\nI\u2019m a big dog man you a runt to me\nMe and Gucci smokin gas, at a round table counting cash\nChop it up by the whole damn\nSelling white girl with no add\n\n[Hook: Gucci Mane]\nIf you smokin, reggie bush\nThen you cannot smoke with me\nIf you wear ..fila, prada, then you can\u2019t walk in with me\nIf you ain\u2019t stuffin a blunt, then y\u2019all niggas can\u2019t smoke with me\nIf you wear fake gold, then you can\u2019t walk in with me\nCan\u2019t walk in with me, yall boys can\u2019t walk in with me\nCan\u2019t walk in with me, girl you can\u2019t walk in with me\nCan\u2019t walk in with me, boy you can\u2019t walk in with me\nNah, walk off enemy, girl you can\u2019t walk in with Guwap\n\n[Verse 3: Migos]\nNo you can\u2019t walk thru with me (hell no)\nDo not respond to temptee\nDrop as on my robin jeans\nVersace, medusa my ring\nI\u2019m clean, just like Mr. Clean, you a peon nigga, your a shrimp\nPut the bag and I\u2019m walking with a limp\n...\nErrybody wanna be a trap god\nBut ain\u2019t plugged in with the trap god\nTrap god, he blessed me, so erryday I wake I gotta thank god\nDiamonds all in my dog tags\nThats a hundrred bands in that louie bag\nAnd a hunhdred bags in that jag\n...\nPack a blunt like my name steve nash..\nAnd a hunned packs in that jag...\n...\n\n[Hook: Gucci Mane]\nIf you smokin, reggie bush\nThen you cannot smoke with me\nIf you wear ..fila, prada, then you can\u2019t walk in with me\nIf you ain\u2019t stuffin a blunt, then y\u2019all niggas can\u2019t smoke with me\nIf you wear fake gold, then you can\u2019t walk in with me\nCan\u2019t walk in with me, yall boys can\u2019t walk in with me\nCan\u2019t walk in with me, girl you can\u2019t walk in with me\nCan\u2019t walk in with me, boy you can\u2019t walk in with me\nNah, walk off enemy, girl you can\u2019t walk in with Guwap", "image": "https://images.genius.com/6f0a4980c8ef838036229e1d4dcd036c.408x408x1.jpg"}], "artist": "Gucci Mane"}