{"songs": [{"title": "Wolf Alternate Intro", "album": null, "year": null, "lyrics": "[Verse 1: Tyler, The Creator]\nSomething something\nMother fucking god again\nI was licking niggas balls until my fucking dick was wet\nBut now these niggas think that I'm weak\nI smoke mother fucking kush you don't even got to speak\nMy niggas smoking on it\nMy niggas toking on it\nI'm swallowing the fucking kush\nY'all niggas choking on it\nAK-47 niggas know I got that money\nNigga I just fucked your bitch and after that I hit my Dougie\nHit my fucking Dougie like it ain't tomorrow\nAsk a bitch does she got some pussy I could borrow\nHit that hit that money I get that\nNigga got a problem get is wig I'mma split that\nOkay okay nigga cause I'm like DJ Quik\nJust the way I quick that\nHit it with finesse\nNiggas know that I'm the best\nNigga do I got grey hair mother fucker do it look like this nigga stressed?\nHell nah\nThese niggas already know\nThat I got bitches and I got hoes\nAnd these niggas already\nWhat the fuck you doing\nWhat the fuck I'm doing counting money though\nNigga uh\nAny nigga got a problem\nNigga better go and solve them\nI'm with your baby mama\nShe Mexican and you already know that she made a nigga enchiladas\nI'm, with these niggas\nMaking that money, counting these figures", "image": "https://images.genius.com/610384882ca6311db99de4fbfcdf2b46.421x421x1.jpg"}], "artist": "Tyler, The Creator"}