{"songs": [{"title": "Weed Roller", "album": "Star Power", "year": "2008-09-17", "lyrics": "[Intro: EZ Wider]\nIt's your boy Mr. EZ Wider\nAnd there's nothing I love more\nThen to come home to a nice fat, bold blunt\nAnd if you feel the same, call up\n\n[Hook: Wiz Khalifa]\nShes my weed roller\nAnd when I'm with her guarantee I'm never sober\nShe know exactly what I need she keep them swishers\nThe way she rolling up that weed I gotta keep her I gotta keep her\n\n[Verse 1: Chevy Woods]\nThat's good weed and she knows so she don't fuck up my swisher\nShe roll that thing that hit hard like a kicker\nI hit the bed and then I get to twist her\nJust like my swisher\nAnd she's my weed roller\nA 50 box she rolled 'em I was like damn\nShe lit the first one up like you know who I am\nMy weed roller\nShe's only good for three blunts then it's over\n\n[Hook: Wiz Khalifa]\nShes my weed roller\nAnd when I'm with her guarantee I'm never sober\nShe know exactly what I need she keep them swishers\nThe way she rolling up that weed I gotta keep her I gotta keep her\n\n[Verse 2: Wiz Khalifa]\nShe know I need that weed as soon I come home off the road\nTo make it easy on me she got one already rolled\nA nice long swisher\nAnd shes a good twister\nYeah I got one that will roll my weed for me\nAnd she don't smoke so that's more weed for me\nNo I can't front this shawty got me impressed\nMake a cigarillo look like a cigarette\n\n[Hook: Wiz Khalifa]\nShes my weed roller\nAnd when I'm with her guarantee I'm never sober\nShe know exactly what I need she keep them swishers\nThe way she rolling up that weed I gotta keep her I gotta keep her", "image": "https://images.genius.com/100d0985ce3b8ee4e2364dd7c94351b4.500x500x1.jpg"}], "artist": "Wiz Khalifa"}