{"songs": [{"title": "Magic", "album": null, "year": null, "lyrics": "Alright baby\nYeah\nI can make the pain disappear\nAnd I can erase the past oh\nI can make the future shine so bright\nAnd I can make right now alright yeah\nI got it you got it we got the magic girl\nI got it you got it we got the magic girl\nI got it you got it we got the magic girl\nI got it you got it we got the magic girl\nAll I got is concrete all around me woo\nBut I can see the countryside\nYou can be rich when you?re poor\nPoor when you're rich\nIt can be raining and I can make the sun shine\n\nI got it you got it we got the magic girl\nI got it (you know you got it baby) you got it we got the magic girl\nI got it (I've got it baby) you got it we got the magic girl\nI got it (You know I got it baby) you got it we got the magic girl\nI know sometimes sometimes you feel no hope\nBut I've been down off that lonely road\nI took whatever gift he offered me\nBecause I knew that he would set me free\n(Whoa) I got it you got it we got the magic girl\nI got it (magic baby) you got it we got the magic (woo) girl\nI got it (we got the magic baby) you got it we got the magic girl\nSkip\nI got it you got it we got the magic girl woo\nScience they can't prove it\nBut I know I can do it\nI can fly\nI can bend metal with my mind\nI can wake up in a paradise oh\n\nWe got that magic\nWe got that magic\nWe got that magic\nWe got that magic\n\nWe got that magic\nWe got that magic\n\nGot that magic come on\nHey\nI got it you got it we got that magic girl\nI got it you got it we got that magic girl\nI got it you got it we got that magic girl\nI got it you got it we got that magic girl\nEveryday", "image": "https://images.genius.com/68262ccdcbffb87427d31b0d6085c2e3.400x400x1.jpg"}], "artist": "T.I."}