{"songs": [{"title": "My Boys", "album": "I\u2019m Up", "year": "2016-02-04", "lyrics": "[Intro]\nLil Durk in this motherfucker, gang, Ralo\nFam, ayy where the real niggas at?\nYou know all the MOB rockin' witcha nigga right here\nYa only the real ones, know what I'm sayin'\n\n[Chorus: Young Thug]\nHey, them my niggas\nYeah, them my boys\nLight him up like he Christmas\nIf he play with my boys\nYeah, them my dogs, them my boys\nYeah, them my niggas, them my boys\nWe gon' ball if she get my boys\nYeah, fuck that bitch if you my boy\nYeah, if you my boys\n\n[Verse 1: Ralo]\nHad a talk with Thug, we was talkin' 'bout Escobar (Pablo!)\nSnitches the only thing a rich nigga stressin' for\nRemember we was riding on the MARTA bus\nThey'd rob the bank before they think 'bout robbing us\nWe did this shit ourself, we ain't ask for no help\nHe'll kill for Terrell, I'll kill for lil' Jeff\nSo now we got right, these niggas went left\nRidin' 'round with them straps, I ain't talkin' seat belts\nI swear to God I'll murk 'em if Thugger say the word\nWe went from robbing these niggas to selling bricks and birds\nThey had the nerve to say they don't like me riding with Thug\nBut at first, they liked to see a friend in clubs\n\n[Chorus: Young Thug]\nHey, them my niggas\nYeah, them my boys\nLight him up like he Christmas\nIf he play with my boys\nYeah, them my dogs, them my boys\nYeah, them my niggas, them my boys\nWe gon' ball if she get my boys\nYeah, fuck that bitch if you my boy\nYeah, if you my boys\n\n[Verse 2: Lil Durk]\nMy niggas turnt, we do it\nPlay crazy smoke like hookah\nRip L'A, what's up Booka\nNo Metro Boomin, boomin'\nOne call, they pull up shooting\nSplash Brothers said we bool\nRoll up some opps in wood\nMy dogs 'nem, they so cuckoo\nToo turnt up for Lil NuNu\nMy niggas demons, voodoo\nThey facing shit like ooVoo, yeah\nFree the gang, we the gang\nThat lil' change made him change\nWe insane, keep a Glock\nIf he strayin', bow-bow\nRob me, nah-nah\n.40 match the sawed off\nFN take his wall off\nLike where is Waldo?\nI'm a street nigga, got my brothers here\nSo fuck you other niggas if you on some other shit\n\n[Chorus: Young Thug]\nHey, them my niggas\nYeah, them my boys\nLight him up like he Christmas\nIf he play with my boys\nYeah, them my dogs, them my boys\nYeah, them my niggas, them my boys\nWe gon' ball if she get my boys\nYeah, fuck that bitch if you my boy\nYeah, if you my boys\n\n[Verse 3: Trouble]\nHundred shots in the daytime if you ever come play with them, my boy\nAin't no shootin' up no random houses, got to get your man, you got to kill that boy\nFree Tre, one of the first niggas to ever put me in that field, my boy\nTook cases be just, my boy\nPolice chasin', we juuged my boy\nGodfather, you know that ain't a question\nHow we rock ain't a question\nY'all still fucking around and got a fresh seven\nMan this shit kinda hectic\nPainful living, growing up missing daddy\nSister making it better\nWhy I be there any time that she need me\n'Cause I know that she had me\nIn and out, but I didn't know my daddy\nEdgewood, Zone 6 shit, rated savage\nYeah, just a project nigga, ain't never had shit\nYoung Day, if you hit me, get nasty, pussy\n\n[Chorus: Young Thug]\nHey, them my niggas\nYeah, them my boys\nLight him up like he Christmas\nIf he play with my boys\nYeah, them my dogs, them my boys\nYeah, them my niggas, them my boys\nWe gon' ball if she get my boys\nYeah, fuck that bitch if you my boy\nYeah, if you my boys\n\n[Verse 4: Young Thug]\nMet that bitch when I was in elementary\nMan them my niggas before elementary\nThey been my niggas ever since elementary\nI swung on his teacher 'bout him, yeah in elementary\nStop all the killing and let's go get it\nWhen you buy you a Bentley, you know you rich\nMe and Ralo, we like Ace Boogie and Mitch\nHe was broke now his shit lit up like he hit a lick\nLil' bitch, slob on the dick\nLil' bitty bitch, my diamonds gon' glisten\nIt's YSL, and Ferragamo shit\nLil Durk with me, tonight we throw the racks on the bitch\n\n[Chorus: Young Thug]\nHey, them my niggas\nYeah, them my boys\nLight him up like he Christmas\nIf he play with my boys\nYeah, them my dogs, them my boys\nYeah, them my niggas, them my boys\nWe gon' ball if she get my boys\nYeah, fuck that bitch if you my boy\nYeah, yeah, if you my boys", "image": "https://images.genius.com/a43ba1522d2954d0ee6a8aca28ff1881.1000x1000x1.jpg"}], "artist": "Young Thug"}